nodepool/__init__.py
nodepool/builder.py
nodepool/config.py
nodepool/exceptions.py
nodepool/launcher.py
nodepool/logconfig.py
nodepool/model_api.py
nodepool/nodeutils.py
nodepool/provider_manager.py
nodepool/stats.py
nodepool/status.py
nodepool/version.py
nodepool/webapp.py
nodepool/cmd/__init__.py
nodepool/cmd/builder.py
nodepool/cmd/config_validator.py
nodepool/cmd/launcher.py
nodepool/cmd/nodepoolcmd.py
nodepool/driver/__init__.py
nodepool/driver/statemachine.py
nodepool/driver/utils.py
nodepool/driver/utils_k8s.py
nodepool/driver/aws/__init__.py
nodepool/driver/aws/adapter.py
nodepool/driver/aws/config.py
nodepool/driver/azure/__init__.py
nodepool/driver/azure/adapter.py
nodepool/driver/azure/azul.py
nodepool/driver/azure/config.py
nodepool/driver/example/__init__.py
nodepool/driver/example/adapter.py
nodepool/driver/example/config.py
nodepool/driver/fake/__init__.py
nodepool/driver/fake/adapter.py
nodepool/driver/fake/config.py
nodepool/driver/gce/__init__.py
nodepool/driver/gce/adapter.py
nodepool/driver/gce/config.py
nodepool/driver/ibmvpc/__init__.py
nodepool/driver/ibmvpc/adapter.py
nodepool/driver/ibmvpc/config.py
nodepool/driver/kubernetes/__init__.py
nodepool/driver/kubernetes/config.py
nodepool/driver/kubernetes/handler.py
nodepool/driver/kubernetes/provider.py
nodepool/driver/metastatic/__init__.py
nodepool/driver/metastatic/adapter.py
nodepool/driver/metastatic/config.py
nodepool/driver/openshift/__init__.py
nodepool/driver/openshift/config.py
nodepool/driver/openshift/handler.py
nodepool/driver/openshift/provider.py
nodepool/driver/openshiftpods/__init__.py
nodepool/driver/openshiftpods/config.py
nodepool/driver/openshiftpods/handler.py
nodepool/driver/openshiftpods/provider.py
nodepool/driver/openstack/__init__.py
nodepool/driver/openstack/adapter.py
nodepool/driver/openstack/config.py
nodepool/driver/static/__init__.py
nodepool/driver/static/config.py
nodepool/driver/static/handler.py
nodepool/driver/static/provider.py
nodepool-11.0.0.dist-info/LICENSE
nodepool-11.0.0.dist-info/METADATA
nodepool-11.0.0.dist-info/WHEEL
nodepool-11.0.0.dist-info/entry_points.txt
nodepool-11.0.0.dist-info/pbr.json
nodepool-11.0.0.dist-info/top_level.txt
nodepool-11.0.0.dist-info/RECORD
