Metadata-Version: 2.1
Name: nodepool
Version: 11.0.0
Summary: Node pool management for a distributed test infrastructure
Home-page: https://zuul-ci.org/
Author: Zuul Team
Author-email: zuul-discuss@lists.zuul-ci.org
Classifier: Intended Audience :: Information Technology
Classifier: Intended Audience :: System Administrators
Classifier: License :: OSI Approved :: Apache Software License
Classifier: Operating System :: POSIX :: Linux
Classifier: Programming Language :: Python
Classifier: Programming Language :: Python :: 3.11
Requires-Python: >= 3.11
License-File: LICENSE
Requires-Dist: Paste
Requires-Dist: PrettyTable <0.8,>=0.6
Requires-Dist: PyYAML
Requires-Dist: WebOb >=1.8.1
Requires-Dist: boto3 >=1.34.141
Requires-Dist: diskimage-builder >=3.36.0
Requires-Dist: extras
Requires-Dist: google-api-python-client
Requires-Dist: ibm-cos-sdk >=2.11.0
Requires-Dist: ibm-platform-services
Requires-Dist: ibm-vpc
Requires-Dist: kazoo ==2.9.0
Requires-Dist: openshift <0.14.0,>=0.13.1
Requires-Dist: openstacksdk !=2.0.0,>=0.103.0
Requires-Dist: paramiko >=2.0.1
Requires-Dist: pbr >=1.3
Requires-Dist: python-daemon >=2.0.4
Requires-Dist: rackspaceauth
Requires-Dist: statsd >=3.0
Requires-Dist: urllib3 >=1.26.0
Requires-Dist: voluptuous
Provides-Extra: nodepool_base
Requires-Dist: objgraph ; extra == 'nodepool_base'
Requires-Dist: python-logstash-async ; extra == 'nodepool_base'
Requires-Dist: yappi ; extra == 'nodepool_base'
Provides-Extra: test
Requires-Dist: coverage ; extra == 'test'
Requires-Dist: fixtures >=0.3.12 ; extra == 'test'
Requires-Dist: flake8 ; extra == 'test'
Requires-Dist: mock >=1.0 ; extra == 'test'
Requires-Dist: moto >=3.1.6 ; extra == 'test'
Requires-Dist: python-subunit ; extra == 'test'
Requires-Dist: responses >=0.12.1 ; extra == 'test'
Requires-Dist: stestr >=1.0.0 ; extra == 'test'
Requires-Dist: testscenarios ; extra == 'test'
Requires-Dist: testtools >=0.9.27 ; extra == 'test'
